{
  "placeholderImages": [
    {
      "id": "gallery-1",
      "description": "Our first meet together. The start of everything.",
      "imageUrl": "/memories/memory20.png",
      "imageHint": "Beggining of our love story"
    },
    {
      "id": "gallery-2",
      "description": "My silly face . Always try to  make you laugh.",
      "imageUrl": "/memories/memory17.png",
      "imageHint": "start feeling one sided love"
    },
    {
      "id": "gallery-3",
      "description": "Your silence started to hurt, but my love for you never wavered. Even when you ignored me, you remained my world.",
      "imageUrl": "/memories/memory18.png",
      "imageHint": "love through pain and separation"
    },
    {
      "id": "gallery-4",
      "description": "Our first visit to the temple together. That's when we truly started to grow closer, feeling the warmth of each other's presence.",
      "imageUrl": "/memories/memory19.png",
      "imageHint": "temple visit and growing closeness"
    },
    {
      "id": "gallery-5",
      "description": "That moment when we were so close, and you kissed me... Time seemed to stop. My heart raced, and the whole world disappeared. It was pure magic, the sweetest moment I've ever felt.",
      "imageUrl": "/memories/memory5.png",
      "imageHint": "our kiss and intimate connection always very special"
    }
  ]
}